Reg_file/reg.v
`ifndef REG_V
`define REG_V

`timescale 1ns/1ps

module reg_file (
    input clk,
    input reset,
    input [4:0] read_reg1, read_reg2, write_reg,
    input [63:0] write_data,
    input reg_write_en,
    output [63:0] read_data1, read_data2
);

// declaring the register file as 32 element array of 64-bit registers and
// following the Big Endian convention
reg [63:0] registers [31:0];

// read operation
assign read_data1 = registers[read_reg1];
assign read_data2 = registers[read_reg2];

// write operation
always @(posedge clk or posedge reset) begin
    if (reset) begin
        for (integer i = 0; i < 32; i = i + 1) 
            registers[i] <= 64'b0;
    end 
    else if (reg_write_en && (write_reg != 0)) 
        registers[write_reg] <= write_data;
end

endmodule

`endif

Reg_file/reg_tb.v
`timescale 1ns/1ps
`include "reg.v"

module reg_tb;
reg [63:0] registers [31:0];
reg clk, reset;
reg [4:0] read_reg1, read_reg2, write_reg;
reg [63:0] write_data;
reg reg_write_en;
wire [63:0] read_data1, read_data2;

// Instantiate
reg_file uut (
    .clk(clk),
    .reset(reset),
    .read_reg1(read_reg1),
    .read_reg2(read_reg2),
    .write_reg(write_reg),
    .write_data(write_data),
    .reg_write_en(reg_write_en)
);

// Testbench stimulus
initial begin
    clk = 0;
    reset = 1;
    #10 reset = 0;
    
    // Test writing to register 5
    write_reg = 5;
    write_data = 64'hDEADBEEFCAFEBABE;
    reg_write_en = 1;
    #10 reg_write_en = 0;

    //  Test reading from register 5
    read_reg1 = 5;
    read_reg2 = 0; // Read from register 0 (should be zero)
    
end

always #5 clk = ~clk;
// writing all the register outputs to file registers.txt
integer file_handle;
integer i;
integer clk_count = 0;
always @(posedge clk)
    clk_count = clk_count + 1;

initial begin
    file_handle = $fopen("registers.txt", "w");

    if (file_handle == 0) begin
        $display("Error: Could not open file.");
        $finish;
    end

    $dumpfile("reg_tb.vcd");
    $dumpvars(0, reg_tb);

    #100;   

    // Writing contents of all registers to file
    for (i = 0; i < 32; i = i + 1) begin
        $fdisplay(file_handle, "%h", uut.registers[i]);
    end

    // Wriing CLock cycles to file
    $fdisplay(file_handle, "%0d", clk_count);

    $fclose(file_handle);
    $finish;
end


endmodule

Reg_file/reg_tb.vcd
$date
	Tue Feb 10 18:01:01 2026
$end
$version
	Icarus Verilog
$end
$timescale
	1ps
$end
$scope module reg_tb $end
$var reg 1 ! clk $end
$var reg 5 " read_reg1 [4:0] $end
$var reg 5 # read_reg2 [4:0] $end
$var reg 1 $ reg_write_en $end
$var reg 1 % reset $end
$var reg 64 & write_data [63:0] $end
$var reg 5 ' write_reg [4:0] $end
$var integer 32 ( clk_count [31:0] $end
$var integer 32 ) file_handle [31:0] $end
$var integer 32 * i [31:0] $end
$scope module uut $end
$var wire 1 ! clk $end
$var wire 64 + read_data1 [63:0] $end
$var wire 64 , read_data2 [63:0] $end
$var wire 5 - read_reg1 [4:0] $end
$var wire 5 . read_reg2 [4:0] $end
$var wire 1 $ reg_write_en $end
$var wire 1 % reset $end
$var wire 64 / write_data [63:0] $end
$var wire 5 0 write_reg [4:0] $end
$var integer 32 1 i [31:0] $end
$upscope $end
$upscope $end
$enddefinitions $end
$comment Show the parameter values. $end
$dumpall
$end
#0
$dumpvars
b100000 1
bx 0
bx /
bx .
bx -
bx ,
bx +
bx *
b10000000000000000000000000000011 )
b0 (
bx '
bx &
1%
x$
bx #
bx "
0!
$end
#5000
b100000 1
b1 (
1!
#10000
0!
1$
b1101111010101101101111101110111111001010111111101011101010111110 &
b1101111010101101101111101110111111001010111111101011101010111110 /
b101 '
b101 0
0%
#15000
b10 (
1!
#20000
0!
b0 ,
b0 #
b0 .
b1101111010101101101111101110111111001010111111101011101010111110 +
b101 "
b101 -
0$
#25000
b11 (
1!
#30000
0!
#35000
b100 (
1!
#40000
0!
#45000
b101 (
1!
#50000
0!
#55000
b110 (
1!
#60000
0!
#65000
b111 (
1!
#70000
0!
#75000
b1000 (
1!
#80000
0!
#85000
b1001 (
1!
#90000
0!
#95000
b1010 (
1!
#100000
0!
b100000 *
