Ins_memory/inst.v
`timescale 1ns/1ps

`define IMEM_SIZE 4096        // max no. of bytes mentioned

module instmem(
    input  wire        clk,
    input  wire        reset,
    input  wire [63:0] addr,      // pc_out of PC
    output reg  [31:0] inst
);

    reg [7:0]  byte_mem [0:`IMEM_SIZE-1];
    reg [31:0] inst_mem [0:(`IMEM_SIZE/4)-1];

    integer i;
    initial begin
        $readmemh("instructions.txt", byte_mem);

        //  4 bytes → 32-bit instruction
        for (i = 0; i < `IMEM_SIZE/4; i = i + 1) begin
            inst_mem[i] = {
                byte_mem[4*i+3],
                byte_mem[4*i+2],
                byte_mem[4*i+1],
                byte_mem[4*i+0]
            };
        end
    end

    // output access logic
    always @(posedge clk) begin
        if (reset)
            inst <= 32'b0;
        else
            inst <= inst_mem[addr[63:2]];   // word aligned access
    end

endmodule

Ins_memory/inst_tb.v
`timescale 1ns/1ps
`include "inst.v"

module inst_tb;

reg clk, reset;
reg [63:0] addr;
wire [31:0] inst;

// Instantiating
instmem dut (
    .clk(clk),
    .reset(reset),
    .addr(addr),
    .inst(inst)
);

always #5 clk = ~clk;
initial begin
    clk = 0;
    reset = 1;
    addr = 0;
    $dumpfile("inst_tb.vcd");
    $dumpvars(0, inst_tb);
    #10;
    reset = 0;
// Reading first 10 instructions from instruction memory
    repeat (10) begin
        #10;
        $display("Time=%0t | PC=%0d | Instruction=%h",
                  $time, addr, inst);

        addr = addr + 4;   // incrementing PC
    end

    #20;
    $finish;
end

endmodule

Ins_memory/inst_tb.vcd
$date
	Tue Feb 10 19:08:49 2026
$end
$version
	Icarus Verilog
$end
$timescale
	1ps
$end
$scope module inst_tb $end
$var wire 32 ! inst [31:0] $end
$var reg 64 " addr [63:0] $end
$var reg 1 # clk $end
$var reg 1 $ reset $end
$scope module dut $end
$var wire 64 % addr [63:0] $end
$var wire 1 # clk $end
$var wire 1 $ reset $end
$var reg 32 & inst [31:0] $end
$var integer 32 ' i [31:0] $end
$upscope $end
$upscope $end
$enddefinitions $end
$comment Show the parameter values. $end
$dumpall
$end
#0
$dumpvars
b10000000000 '
bx &
b0 %
1$
0#
b0 "
bx !
$end
#5000
b0 !
b0 &
1#
#10000
0#
0$
#15000
b10011000000010101000000000000 !
b10011000000010101000000000000 &
1#
#20000
0#
b100 "
b100 %
#25000
b10010011000000011010000000000000 !
b10010011000000011010000000000000 &
1#
#30000
0#
b1000 "
b1000 %
#35000
b10110011000000000011000100000000 !
b10110011000000000011000100000000 &
1#
#40000
0#
b1100 "
b1100 %
#45000
b110011000000010011000101000000 !
b110011000000010011000101000000 &
1#
#50000
0#
b10000 "
b10000 %
#55000
b110011111100100011000100000000 !
b110011111100100011000100000000 &
1#
#60000
0#
b10100 "
b10100 %
#65000
b10110011111100100100000100000000 !
b10110011111100100100000100000000 &
1#
#70000
0#
b11000 "
b11000 %
#75000
b110011011000110100000100000000 !
b110011011000110100000100000000 &
1#
#80000
0#
b11100 "
b11100 %
#85000
b10110011011000110011000100000000 !
b10110011011000110011000100000000 &
1#
#90000
0#
b100000 "
b100000 %
#95000
b100011101100000001001000000000 !
b100011101100000001001000000000 &
1#
#100000
0#
b100100 "
b100100 %
#105000
b11101101010000001000000000 !
b11101101010000001000000000 &
1#
#110000
0#
b101000 "
b101000 %
#115000
b10100011101100010110001000000000 !
b10100011101100010110001000000000 &
1#
